unvivtool.cpython-312-x86_64-linux-musl.so
unvivtool-3.12.dist-info/METADATA
unvivtool-3.12.dist-info/WHEEL
unvivtool-3.12.dist-info/top_level.txt
unvivtool-3.12.dist-info/RECORD
unvivtool-3.12.dist-info/licenses/LICENSE
