Metadata-Version: 2.4
Name: unvivtool
Version: 3.12
Summary: simple BIGF BIGH BIG4 decoder/encoder (commonly known as VIV/BIG)
Home-page: https://github.com/bfut/unvivtool
Author: Benjamin Futasz
License: GPLv3+
Requires-Python: >=3.10
License-File: LICENSE
Dynamic: author
Dynamic: description
Dynamic: description-content-type
Dynamic: home-page
Dynamic: license
Dynamic: license-file
Dynamic: requires-python
Dynamic: summary
